jupyter_cache/__init__.py
jupyter_cache/base.py
jupyter_cache/entry_points.py
jupyter_cache/readers.py
jupyter_cache/utils.py
jupyter_cache/cache/__init__.py
jupyter_cache/cache/db.py
jupyter_cache/cache/main.py
jupyter_cache/cli/__init__.py
jupyter_cache/cli/arguments.py
jupyter_cache/cli/options.py
jupyter_cache/cli/utils.py
jupyter_cache/cli/commands/__init__.py
jupyter_cache/cli/commands/cmd_cache.py
jupyter_cache/cli/commands/cmd_main.py
jupyter_cache/cli/commands/cmd_notebook.py
jupyter_cache/cli/commands/cmd_project.py
jupyter_cache/executors/__init__.py
jupyter_cache/executors/base.py
jupyter_cache/executors/basic.py
jupyter_cache/executors/utils.py
jupyter_cache-0.6.0.dist-info/entry_points.txt
jupyter_cache-0.6.0.dist-info/LICENSE
jupyter_cache-0.6.0.dist-info/WHEEL
jupyter_cache-0.6.0.dist-info/METADATA
jupyter_cache-0.6.0.dist-info/RECORD
