Metadata-Version: 2.1
Name: jupyter-cache
Version: 0.6.0
Summary: A defined interface for working with a cache of jupyter notebooks.
Keywords: sphinx extension material design web components
Author-email: Chris Sewell <chrisj_sewell@hotmail.com>
Requires-Python: ~=3.8
Classifier: Development Status :: 4 - Beta
Classifier: Framework :: Sphinx :: Extension
Classifier: Intended Audience :: Developers
Classifier: License :: OSI Approved :: MIT License
Classifier: Programming Language :: Python :: 3
Classifier: Programming Language :: Python :: 3.8
Classifier: Programming Language :: Python :: 3.9
Classifier: Programming Language :: Python :: 3.10
Classifier: Programming Language :: Python :: 3.11
Classifier: Programming Language :: Python :: Implementation :: CPython
Classifier: Topic :: Software Development :: Libraries :: Python Modules
Requires-Dist: attrs
Requires-Dist: click
Requires-Dist: importlib-metadata
Requires-Dist: nbclient>=0.2,<0.8
Requires-Dist: nbformat
Requires-Dist: pyyaml
Requires-Dist: sqlalchemy>=1.3.12,<3
Requires-Dist: tabulate
Requires-Dist: click-log ; extra == "cli"
Requires-Dist: pre-commit>=2.12,<4.0 ; extra == "code_style"
Requires-Dist: nbdime ; extra == "rtd"
Requires-Dist: ipykernel ; extra == "rtd"
Requires-Dist: jupytext ; extra == "rtd"
Requires-Dist: myst-nb ; extra == "rtd"
Requires-Dist: sphinx-book-theme ; extra == "rtd"
Requires-Dist: sphinx-copybutton ; extra == "rtd"
Requires-Dist: nbdime ; extra == "testing"
Requires-Dist: coverage ; extra == "testing"
Requires-Dist: ipykernel ; extra == "testing"
Requires-Dist: jupytext ; extra == "testing"
Requires-Dist: matplotlib ; extra == "testing"
Requires-Dist: nbformat>=5.1 ; extra == "testing"
Requires-Dist: numpy ; extra == "testing"
Requires-Dist: pandas ; extra == "testing"
Requires-Dist: pytest>=6,<8 ; extra == "testing"
Requires-Dist: pytest-cov ; extra == "testing"
Requires-Dist: pytest-regressions ; extra == "testing"
Requires-Dist: sympy ; extra == "testing"
Project-URL: Documentation, https://jupyter-cache.readthedocs.io
Project-URL: Homepage, https://github.com/executablebooks/jupyter-cache
Provides-Extra: cli
Provides-Extra: code_style
Provides-Extra: rtd
Provides-Extra: testing
